setup.py
apollo_cli/__init__.py
apollo_cli/apollo.py
apollo_cli/apollo_exceptions.py
apollo_cli/cassandra_handler.py
apollo_cli/cassandra_snapshot_exclude.py
apollo_cli/constants.py
apollo_cli/notifier.py
apollo_cli/snapshot_metadata.py
apollo_cli/snapshot_repository.py
apollo_cli/utils.py
apollo_cli.egg-info/PKG-INFO
apollo_cli.egg-info/SOURCES.txt
apollo_cli.egg-info/dependency_links.txt
apollo_cli.egg-info/entry_points.txt
apollo_cli.egg-info/requires.txt
apollo_cli.egg-info/top_level.txt